cytetype/__init__.py
cytetype/config.py
cytetype/main.py
cytetype/api/__init__.py
cytetype/api/client.py
cytetype/api/exceptions.py
cytetype/api/progress.py
cytetype/api/schemas.py
cytetype/api/transport.py
cytetype/core/__init__.py
cytetype/core/payload.py
cytetype/core/results.py
cytetype/preprocessing/__init__.py
cytetype/preprocessing/aggregation.py
cytetype/preprocessing/extraction.py
cytetype/preprocessing/validation.py
cytetype-0.13.0.dist-info/licenses/LICENSE.md
tests/conftest.py
tests/test_cytetype_integration.py
cytetype-0.13.0.dist-info/METADATA
cytetype-0.13.0.dist-info/WHEEL
cytetype-0.13.0.dist-info/top_level.txt
cytetype-0.13.0.dist-info/RECORD
