Metadata-Version: 2.4
Name: cytetype
Version: 0.13.0
Summary: Python client for characterization of clusters from single-cell RNA-seq data.
Author-email: Parashar Dhapola <parashar@nygen.io>
License: CC BY-NC-SA 4.0
Project-URL: Homepage, https://github.com/NygenAnalytics/cytetype
Project-URL: Issues, https://github.com/NygenAnalytics/cytetype/issues
Project-URL: Repository, https://github.com/NygenAnalytics/cytetype
Keywords: bioinformatics,single-cell,RNA-seq,annotation,cell types
Requires-Python: >=3.12
License-File: LICENSE.md
Requires-Dist: anndata~=0.12.7
Requires-Dist: loguru~=0.7.3
Requires-Dist: natsort~=8.4.0
Requires-Dist: requests~=2.32.5
Requires-Dist: pydantic~=2.12.5
Requires-Dist: session-info~=1.0.1
Requires-Dist: python-dotenv~=1.2.1
Dynamic: license-file
